webcon/__init__.py
webcon/webcon.py
webcon/static/css/style.css
webcon/static/css/skeleton/LICENSE.md
webcon/static/css/skeleton/normalize.css
webcon/static/css/skeleton/skeleton.css
webcon/views/base.tpl
webcon/views/index.tpl
webcon/views/service.tpl
webcon-1.0.2.dist-info/DESCRIPTION.rst
webcon-1.0.2.dist-info/METADATA
webcon-1.0.2.dist-info/RECORD
webcon-1.0.2.dist-info/WHEEL
webcon-1.0.2.dist-info/entry_points.txt
webcon-1.0.2.dist-info/metadata.json
webcon-1.0.2.dist-info/top_level.txt
