Metadata-Version: 2.0
Name: webcon
Version: 1.0.2
Summary: Control your computer from a web interface
Home-page: https://github.com/metakirby5/webcon
Author: Ethan Chan
Author-email: metakirby5@gmail.com
License: MIT
Keywords: web controller config yaml
Platform: UNKNOWN
Classifier: Development Status :: 2 - Pre-Alpha
Classifier: Environment :: Web Environment
Classifier: Intended Audience :: End Users/Desktop
Classifier: Topic :: Utilities
Classifier: License :: OSI Approved :: MIT License
Classifier: Natural Language :: English
Classifier: Operating System :: POSIX
Classifier: Programming Language :: Python :: 3
Requires-Dist: argcomplete
Requires-Dist: bottle
Requires-Dist: termcolor
Requires-Dist: PyYAML
